combin/delayed_ops/and2_d.vhd
library ieee;
use ieee.std_logic_1164.all;

entity and2_d is
    port (
        a : in std_logic;
        b : in std_logic;
        o : out std_logic
    );
end and2_d;

architecture rtl of and2_d is

begin

    o <= a and b after 10 ns;

end architecture;

combin/delayed_ops/xor2_d.vhd
library ieee;
use ieee.std_logic_1164.all;

entity xor2_d is
    port (
        a : in std_logic;
        b : in std_logic;
        o : out std_logic
    );
end xor2_d;

architecture rtl of xor2_d is

begin

    o <= a xor b after 10 ns;

end architecture;

combin/delayed_ops/or2_d.vhd
library ieee;
use ieee.std_logic_1164.all;

entity or2_d is
    port (
        a : in std_logic;
        b : in std_logic;
        o : out std_logic
    );
end or2_d;

architecture rtl of or2_d is

begin

    o <= a or b after 10 ns;

end architecture;

seq/mod_circ01_seq.vhd
library ieee;
use ieee.std_logic_1164.all;
use ieee.numeric_std.all;
use work.delayed_operators.all;

entity mod_circ01_seq is
    port (
        clk : in std_logic;
        i : in std_logic_vector(3 downto 0);
        o : out std_logic_vector(1 downto 0)
    );
end entity;

architecture rtl of mod_circ01_seq is

    signal s11a, s11b, s12a, s12b : std_logic;
    signal tmp : std_logic; -- For dummy condition willingly added
    signal s31 : std_logic;

    -- Added signals 
    signal s21, s22, s23 : std_logic; -- could have been named sHT1 and sHT2
begin
    

    P11 : and2_d port map (i(0), i(1), s11a);
    P12 : or2_d port map (i(2), i(3), s12a);

    process (clk)
    begin
        if clk = '1' then
            s11b <= s11a;
            s12b <= s12a;
        end if;
    end process;

    P21 : and2_d port map (s11b, s12b, s23); -- added gate HT
    P22 : xor2_d port map (s11b, s23, s22); -- added gate HT
    P23 : xor2_d port map (s11b, s12b, s21); 
    P31 : and2_d port map (s22, s21, s31); -- modified relations

    process (clk)
    begin
        if clk = '1' then
                o(0) <= s31;
                o(1) <= s21;
        end if;
    end process;

end architecture;

seq/circ01_seq.vhd
library ieee;
use ieee.std_logic_1164.all;
use ieee.numeric_std.all;
use work.delayed_operators.all;

entity circ01_seq is
    port (
        clk : in std_logic;
        i : in std_logic_vector(3 downto 0);
        o : out std_logic_vector(1 downto 0)
    );
end entity;

architecture rtl of circ01_seq is
    signal s11a, s11b, s12a, s12b, s21, s31 : std_logic;
begin

    P11 : and2_d port map (i(0), i(1), s11a);
    P12 : or2_d port map (i(2), i(3), s12a);

    process(clk) -- Synchronous register barrier 
    begin
        if clk = '1' then
            s11b <= s11a;
            s12b <= s12a;
        end if;
    end process;

    P21 : xor2_d port map (s11b, s12b, s21);
    P22 : and2_d port map (s11b, s21, s31);



    process(clk)
    begin
        if clk = '1' then
            o(0) <= s31;
            o(1) <= s21;
        end if;
    end process;
    
end architecture;

seq/tb_comp_seq.vhd
library ieee;
use ieee.std_logic_1164.all;
use ieee.numeric_std.all;
use work.delayed_operators.all;

entity tb_comp_seq is 
end entity;

architecture rtl of tb_comp_seq is

    constant T : time := 50 ns;

    procedure wait_cycles(n : natural) is
    begin
        for i in 0 to n-1 loop
            wait for T;
        end loop; 
    end procedure;

    procedure wait1 is
    begin
        wait for T;
    end procedure;


    signal clk_init : std_logic := '1';
    signal clk_2x : std_logic := '1';
    signal clk_4x : std_logic := '1';
    signal clk_8x : std_logic := '1';

    signal tb_input_vector : std_logic_vector(3 downto 0);
    signal tb_output_vector_auth : std_logic_vector(1 downto 0);
    signal tb_output_vector_inf : std_logic_vector(1 downto 0);

    signal tb_clk_init_output_auth : std_logic_vector(1 downto 0);
    signal tb_clk_2x_output_auth : std_logic_vector(1 downto 0);
    signal tb_clk_4x_output_auth : std_logic_vector(1 downto 0);
    signal tb_clk_8x_output_auth : std_logic_vector(1 downto 0);

    signal tb_clk_init_output_inf : std_logic_vector(1 downto 0);
    signal tb_clk_2x_output_inf : std_logic_vector(1 downto 0);
    signal tb_clk_4x_output_inf : std_logic_vector(1 downto 0);
    signal tb_clk_8x_output_inf : std_logic_vector(1 downto 0);

begin

    clk_init <= not(clk_init) after T/2;
    clk_2x <= not(clk_2x) after T/4;
    clk_4x <= not(clk_4x) after T/8;
    clk_8x <= not(clk_8x) after T/16;

    uut_auth_init : entity work.circ01_seq
    port map(
        clk => clk_init,
        i => tb_input_vector,
        o => tb_clk_init_output_auth
    );
    
    uut_inf_init : entity work.mod_circ01_seq
    port map(
        clk => clk_init,
        i => tb_input_vector,
        o => tb_clk_init_output_inf
    );

    uut_auth_2x : entity work.circ01_seq
    port map(
        clk => clk_2x,
        i => tb_input_vector,
        o => tb_clk_2x_output_auth
    );
    
    uut_inf_2x : entity work.mod_circ01_seq
    port map(
        clk => clk_2x,
        i => tb_input_vector,
        o => tb_clk_2x_output_inf
    );

    uut_auth_4x : entity work.circ01_seq
    port map(
        clk => clk_4x,
        i => tb_input_vector,
        o => tb_clk_4x_output_auth
    );
    
    uut_inf_4x : entity work.mod_circ01_seq
    port map(
        clk => clk_4x,
        i => tb_input_vector,
        o => tb_clk_4x_output_inf
    );

    uut_auth_8x : entity work.circ01_seq
    port map(
        clk => clk_8x,
        i => tb_input_vector,
        o => tb_clk_8x_output_auth
    );
    
    uut_inf_8x : entity work.mod_circ01_seq
    port map(
        clk => clk_8x,
        i => tb_input_vector,
        o => tb_clk_8x_output_inf
    );

    process 
    begin 
        for i in 0 to 15 loop
            wait1; 
            tb_input_vector <= std_logic_vector(to_unsigned(i, 4));
        end loop; 

        wait;
    end process;

end architecture;

seq/test_seq.vcd
$date
  Mon Mar  6 11:00:36 2023
$end
$version
  GHDL v0
$end
$timescale
  1 fs
$end
$scope module standard $end
$upscope $end
$scope module std_logic_1164 $end
$upscope $end
$scope module numeric_std $end
$upscope $end
$scope module delayed_operators $end
$upscope $end
$scope module tb_comp_seq $end
$var reg 1 ! clk_init $end
$var reg 1 " clk_2x $end
$var reg 1 # clk_4x $end
$var reg 1 $ clk_8x $end
$var reg 4 % tb_input_vector[3:0] $end
$var reg 2 & tb_output_vector_auth[1:0] $end
$var reg 2 ' tb_output_vector_inf[1:0] $end
$var reg 2 ( tb_clk_init_output_auth[1:0] $end
$var reg 2 ) tb_clk_2x_output_auth[1:0] $end
$var reg 2 * tb_clk_4x_output_auth[1:0] $end
$var reg 2 + tb_clk_8x_output_auth[1:0] $end
$var reg 2 , tb_clk_init_output_inf[1:0] $end
$var reg 2 - tb_clk_2x_output_inf[1:0] $end
$var reg 2 . tb_clk_4x_output_inf[1:0] $end
$var reg 2 / tb_clk_8x_output_inf[1:0] $end
$scope module uut_auth_init $end
$var reg 1 0 clk $end
$var reg 4 1 i[3:0] $end
$var reg 2 2 o[1:0] $end
$var reg 1 3 s11a $end
$var reg 1 4 s11b $end
$var reg 1 5 s12a $end
$var reg 1 6 s12b $end
$var reg 1 7 s21 $end
$var reg 1 8 s31 $end
$scope module p11 $end
$var reg 1 9 a $end
$var reg 1 : b $end
$var reg 1 ; o $end
$upscope $end
$scope module p12 $end
$var reg 1 < a $end
$var reg 1 = b $end
$var reg 1 > o $end
$upscope $end
$scope module p21 $end
$var reg 1 ? a $end
$var reg 1 @ b $end
$var reg 1 A o $end
$upscope $end
$scope module p22 $end
$var reg 1 B a $end
$var reg 1 C b $end
$var reg 1 D o $end
$upscope $end
$upscope $end
$scope module uut_inf_init $end
$var reg 1 E clk $end
$var reg 4 F i[3:0] $end
$var reg 2 G o[1:0] $end
$var reg 1 H s11a $end
$var reg 1 I s11b $end
$var reg 1 J s12a $end
$var reg 1 K s12b $end
$var reg 1 L tmp $end
$var reg 1 M s31 $end
$var reg 1 N s21 $end
$var reg 1 O s22 $end
$var reg 1 P s23 $end
$scope module p11 $end
$var reg 1 Q a $end
$var reg 1 R b $end
$var reg 1 S o $end
$upscope $end
$scope module p12 $end
$var reg 1 T a $end
$var reg 1 U b $end
$var reg 1 V o $end
$upscope $end
$scope module p21 $end
$var reg 1 W a $end
$var reg 1 X b $end
$var reg 1 Y o $end
$upscope $end
$scope module p22 $end
$var reg 1 Z a $end
$var reg 1 [ b $end
$var reg 1 \ o $end
$upscope $end
$scope module p23 $end
$var reg 1 ] a $end
$var reg 1 ^ b $end
$var reg 1 _ o $end
$upscope $end
$scope module p31 $end
$var reg 1 ` a $end
$var reg 1 a b $end
$var reg 1 b o $end
$upscope $end
$upscope $end
$scope module uut_auth_2x $end
$var reg 1 c clk $end
$var reg 4 d i[3:0] $end
$var reg 2 e o[1:0] $end
$var reg 1 f s11a $end
$var reg 1 g s11b $end
$var reg 1 h s12a $end
$var reg 1 i s12b $end
$var reg 1 j s21 $end
$var reg 1 k s31 $end
$scope module p11 $end
$var reg 1 l a $end
$var reg 1 m b $end
$var reg 1 n o $end
$upscope $end
$scope module p12 $end
$var reg 1 o a $end
$var reg 1 p b $end
$var reg 1 q o $end
$upscope $end
$scope module p21 $end
$var reg 1 r a $end
$var reg 1 s b $end
$var reg 1 t o $end
$upscope $end
$scope module p22 $end
$var reg 1 u a $end
$var reg 1 v b $end
$var reg 1 w o $end
$upscope $end
$upscope $end
$scope module uut_inf_2x $end
$var reg 1 x clk $end
$var reg 4 y i[3:0] $end
$var reg 2 z o[1:0] $end
$var reg 1 { s11a $end
$var reg 1 | s11b $end
$var reg 1 } s12a $end
$var reg 1 !" s12b $end
$var reg 1 "" tmp $end
$var reg 1 #" s31 $end
$var reg 1 $" s21 $end
$var reg 1 %" s22 $end
$var reg 1 &" s23 $end
$scope module p11 $end
$var reg 1 '" a $end
$var reg 1 (" b $end
$var reg 1 )" o $end
$upscope $end
$scope module p12 $end
$var reg 1 *" a $end
$var reg 1 +" b $end
$var reg 1 ," o $end
$upscope $end
$scope module p21 $end
$var reg 1 -" a $end
$var reg 1 ." b $end
$var reg 1 /" o $end
$upscope $end
$scope module p22 $end
$var reg 1 0" a $end
$var reg 1 1" b $end
$var reg 1 2" o $end
$upscope $end
$scope module p23 $end
$var reg 1 3" a $end
$var reg 1 4" b $end
$var reg 1 5" o $end
$upscope $end
$scope module p31 $end
$var reg 1 6" a $end
$var reg 1 7" b $end
$var reg 1 8" o $end
$upscope $end
$upscope $end
$scope module uut_auth_4x $end
$var reg 1 9" clk $end
$var reg 4 :" i[3:0] $end
$var reg 2 ;" o[1:0] $end
$var reg 1 <" s11a $end
$var reg 1 =" s11b $end
$var reg 1 >" s12a $end
$var reg 1 ?" s12b $end
$var reg 1 @" s21 $end
$var reg 1 A" s31 $end
$scope module p11 $end
$var reg 1 B" a $end
$var reg 1 C" b $end
$var reg 1 D" o $end
$upscope $end
$scope module p12 $end
$var reg 1 E" a $end
$var reg 1 F" b $end
$var reg 1 G" o $end
$upscope $end
$scope module p21 $end
$var reg 1 H" a $end
$var reg 1 I" b $end
$var reg 1 J" o $end
$upscope $end
$scope module p22 $end
$var reg 1 K" a $end
$var reg 1 L" b $end
$var reg 1 M" o $end
$upscope $end
$upscope $end
$scope module uut_inf_4x $end
$var reg 1 N" clk $end
$var reg 4 O" i[3:0] $end
$var reg 2 P" o[1:0] $end
$var reg 1 Q" s11a $end
$var reg 1 R" s11b $end
$var reg 1 S" s12a $end
$var reg 1 T" s12b $end
$var reg 1 U" tmp $end
$var reg 1 V" s31 $end
$var reg 1 W" s21 $end
$var reg 1 X" s22 $end
$var reg 1 Y" s23 $end
$scope module p11 $end
$var reg 1 Z" a $end
$var reg 1 [" b $end
$var reg 1 \" o $end
$upscope $end
$scope module p12 $end
$var reg 1 ]" a $end
$var reg 1 ^" b $end
$var reg 1 _" o $end
$upscope $end
$scope module p21 $end
$var reg 1 `" a $end
$var reg 1 a" b $end
$var reg 1 b" o $end
$upscope $end
$scope module p22 $end
$var reg 1 c" a $end
$var reg 1 d" b $end
$var reg 1 e" o $end
$upscope $end
$scope module p23 $end
$var reg 1 f" a $end
$var reg 1 g" b $end
$var reg 1 h" o $end
$upscope $end
$scope module p31 $end
$var reg 1 i" a $end
$var reg 1 j" b $end
$var reg 1 k" o $end
$upscope $end
$upscope $end
$scope module uut_auth_8x $end
$var reg 1 l" clk $end
$var reg 4 m" i[3:0] $end
$var reg 2 n" o[1:0] $end
$var reg 1 o" s11a $end
$var reg 1 p" s11b $end
$var reg 1 q" s12a $end
$var reg 1 r" s12b $end
$var reg 1 s" s21 $end
$var reg 1 t" s31 $end
$scope module p11 $end
$var reg 1 u" a $end
$var reg 1 v" b $end
$var reg 1 w" o $end
$upscope $end
$scope module p12 $end
$var reg 1 x" a $end
$var reg 1 y" b $end
$var reg 1 z" o $end
$upscope $end
$scope module p21 $end
$var reg 1 {" a $end
$var reg 1 |" b $end
$var reg 1 }" o $end
$upscope $end
$scope module p22 $end
$var reg 1 !# a $end
$var reg 1 "# b $end
$var reg 1 ## o $end
$upscope $end
$upscope $end
$scope module uut_inf_8x $end
$var reg 1 $# clk $end
$var reg 4 %# i[3:0] $end
$var reg 2 &# o[1:0] $end
$var reg 1 '# s11a $end
$var reg 1 (# s11b $end
$var reg 1 )# s12a $end
$var reg 1 *# s12b $end
$var reg 1 +# tmp $end
$var reg 1 ,# s31 $end
$var reg 1 -# s21 $end
$var reg 1 .# s22 $end
$var reg 1 /# s23 $end
$scope module p11 $end
$var reg 1 0# a $end
$var reg 1 1# b $end
$var reg 1 2# o $end
$upscope $end
$scope module p12 $end
$var reg 1 3# a $end
$var reg 1 4# b $end
$var reg 1 5# o $end
$upscope $end
$scope module p21 $end
$var reg 1 6# a $end
$var reg 1 7# b $end
$var reg 1 8# o $end
$upscope $end
$scope module p22 $end
$var reg 1 9# a $end
$var reg 1 :# b $end
$var reg 1 ;# o $end
$upscope $end
$scope module p23 $end
$var reg 1 <# a $end
$var reg 1 =# b $end
$var reg 1 ># o $end
$upscope $end
$scope module p31 $end
$var reg 1 ?# a $end
$var reg 1 @# b $end
$var reg 1 A# o $end
$upscope $end
$upscope $end
$upscope $end
$enddefinitions $end
#0
1!
1"
1#
1$
bUUUU %
bUU &
bUU '
bUU (
bUU )
bUU *
bUU +
bUU ,
bUU -
bUU .
bUU /
10
bUUUU 1
bUU 2
U3
U4
U5
U6
U7
U8
U9
U:
U;
U<
U=
U>
U?
U@
UA
UB
UC
UD
1E
bUUUU F
bUU G
UH
UI
UJ
UK
UL
UM
UN
UO
UP
UQ
UR
US
UT
UU
UV
UW
UX
UY
UZ
U[
U\
U]
U^
U_
U`
Ua
Ub
1c
bUUUU d
bUU e
Uf
Ug
Uh
Ui
Uj
Uk
Ul
Um
Un
Uo
Up
Uq
Ur
Us
Ut
Uu
Uv
Uw
1x
bUUUU y
bUU z
U{
U|
U}
U!"
U""
U#"
U$"
U%"
U&"
U'"
U("
U)"
U*"
U+"
U,"
U-"
U."
U/"
U0"
U1"
U2"
U3"
U4"
U5"
U6"
U7"
U8"
19"
bUUUU :"
bUU ;"
U<"
U="
U>"
U?"
U@"
UA"
UB"
UC"
UD"
UE"
UF"
UG"
UH"
UI"
UJ"
UK"
UL"
UM"
1N"
bUUUU O"
bUU P"
UQ"
UR"
US"
UT"
UU"
UV"
UW"
UX"
UY"
UZ"
U["
U\"
U]"
U^"
U_"
U`"
Ua"
Ub"
Uc"
Ud"
Ue"
Uf"
Ug"
Uh"
Ui"
Uj"
Uk"
1l"
bUUUU m"
bUU n"
Uo"
Up"
Uq"
Ur"
Us"
Ut"
Uu"
Uv"
Uw"
Ux"
Uy"
Uz"
U{"
U|"
U}"
U!#
U"#
U##
1$#
bUUUU %#
bUU &#
U'#
U(#
U)#
U*#
U+#
U,#
U-#
U.#
U/#
U0#
U1#
U2#
U3#
U4#
U5#
U6#
U7#
U8#
U9#
U:#
U;#
U<#
U=#
U>#
U?#
U@#
UA#
#3125000
0$
0l"
0$#
#6250000
0#
1$
09"
0N"
1l"
1$#
#9375000
0$
0l"
0$#
#10000000
U;
U>
UA
UD
US
UV
UY
U\
U_
Ub
Un
Uq
Ut
Uw
U)"
U,"
U/"
U2"
U5"
U8"
UD"
UG"
UJ"
UM"
U\"
U_"
Ub"
Ue"
Uh"
Uk"
Uw"
Uz"
U}"
U##
U2#
U5#
U8#
U;#
U>#
UA#
#12500000
0"
1#
1$
0c
0x
19"
1N"
1l"
1$#
#15625000
0$
0l"
0$#
#18750000
0#
1$
09"
0N"
1l"
1$#
#21875000
0$
0l"
0$#
#25000000
0!
1"
1#
1$
00
0E
1c
1x
19"
1N"
1l"
1$#
#28125000
0$
0l"
0$#
#31250000
0#
1$
09"
0N"
1l"
1$#
#34375000
0$
0l"
0$#
#37500000
0"
1#
1$
0c
0x
19"
1N"
1l"
1$#
#40625000
0$
0l"
0$#
#43750000
0#
1$
09"
0N"
1l"
1$#
#46875000
0$
0l"
0$#
#50000000
1!
1"
1#
1$
b0000 %
10
b0000 1
09
0:
0<
0=
1E
b0000 F
0Q
0R
0T
0U
1c
b0000 d
0l
0m
0o
0p
1x
b0000 y
0'"
0("
0*"
0+"
19"
b0000 :"
0B"
0C"
0E"
0F"
1N"
b0000 O"
0Z"
0["
0]"
0^"
1l"
b0000 m"
0u"
0v"
0x"
0y"
1$#
b0000 %#
00#
01#
03#
04#
#53125000
0$
0l"
0$#
#56250000
0#
1$
09"
0N"
1l"
1$#
#59375000
0$
0l"
0$#
#60000000
03
05
0;
0>
0H
0J
0S
0V
0f
0h
0n
0q
0{
0}
0)"
0,"
0<"
0>"
0D"
0G"
0Q"
0S"
0\"
0_"
0o"
0q"
0w"
0z"
0'#
0)#
02#
05#
#62500000
0"
1#
1$
0c
0x
19"
0="
0?"
0H"
0I"
0K"
1N"
0R"
0T"
0`"
0a"
0c"
0f"
0g"
1l"
0p"
0r"
0{"
0|"
0!#
1$#
0(#
0*#
06#
07#
09#
0<#
0=#
#65625000
0$
0l"
0$#
#68750000
0#
1$
09"
0N"
1l"
1$#
#71875000
0$
0l"
0$#
#72500000
0@"
0A"
0J"
0L"
0M"
0W"
0Y"
0b"
0d"
Ue"
0h"
0j"
0s"
0t"
0}"
0"#
0##
0-#
0/#
08#
0:#
U;#
0>#
0@#
#75000000
0!
1"
1#
1$
b00 *
b00 +
b0U .
b0U /
00
0E
1c
0g
0i
0r
0s
0u
1x
0|
0!"
0-"
0."
00"
03"
04"
19"
b00 ;"
1N"
b0U P"
1l"
b00 n"
1$#
b0U &#
#78125000
0$
0l"
0$#
#81250000
0#
1$
09"
0N"
1l"
1$#
#82500000
0M"
0V"
0X"
0e"
0i"
0k"
0##
0,#
0.#
0;#
0?#
0A#
#84375000
0$
0l"
0$#
#85000000
0j
0k
0t
0v
0w
0$"
0&"
0/"
01"
U2"
05"
07"
#87500000
0"
1#
1$
b00 .
b00 /
0c
0x
19"
1N"
b00 P"
1l"
1$#
b00 &#
#90625000
0$
0l"
0$#
#92500000
0k"
0A#
#93750000
0#
1$
09"
0N"
1l"
1$#
#95000000
0w
0#"
0%"
02"
06"
08"
#96875000
0$
0l"
0$#
#100000000
1!
1"
1#
1$
b0001 %
b00 )
b00 -
10
b0001 1
04
06
19
0?
0@
0B
1E
b0001 F
0I
0K
1Q
0W
0X
0Z
0]
0^
1c
b0001 d
b00 e
1l
1x
b0001 y
b00 z
1'"
19"
b0001 :"
1B"
1N"
b0001 O"
1Z"
1l"
b0001 m"
1u"
1$#
b0001 %#
10#
#103125000
0$
0l"
0$#
#105000000
08"
#106250000
0#
1$
09"
0N"
1l"
1$#
#109375000
0$
0l"
0$#
#110000000
07
08
0;
0A
0C
0D
0N
0P
0S
0Y
0[
U\
0_
0a
0n
0)"
0D"
0\"
0w"
02#
#112500000
0"
1#
1$
0c
0x
19"
1N"
1l"
1$#
#115625000
0$
0l"
0$#
#118750000
0#
1$
09"
0N"
1l"
1$#
#120000000
0D
0M
0O
0\
0`
0b
#121875000
0$
0l"
0$#
#125000000
0!
1"
1#
1$
00
0E
1c
1x
19"
1N"
1l"
1$#
#128125000
0$
0l"
0$#
#130000000
0b
#131250000
0#
1$
09"
0N"
1l"
1$#
#134375000
0$
0l"
0$#
#137500000
0"
1#
1$
0c
0x
19"
1N"
1l"
1$#
#140625000
0$
0l"
0$#
#143750000
0#
1$
09"
0N"
1l"
1$#
#146875000
0$
0l"
0$#
#150000000
1!
1"
1#
1$
b0010 %
b00 (
b00 ,
10
b0010 1
b00 2
09
1:
1E
b0010 F
b00 G
0Q
1R
1c
b0010 d
0l
1m
1x
b0010 y
0'"
1("
19"
b0010 :"
0B"
1C"
1N"
b0010 O"
0Z"
1["
1l"
b0010 m"
0u"
1v"
1$#
b0010 %#
00#
11#
#153125000
0$
0l"
0$#
#156250000
0#
1$
09"
0N"
1l"
1$#
#159375000
0$
0l"
0$#
#160000000
0;
0S
0n
0)"
0D"
0\"
0w"
02#
#162500000
0"
1#
1$
0c
0x
19"
1N"
1l"
1$#
#165625000
0$
0l"
0$#
#168750000
0#
1$
09"
0N"
1l"
1$#
#171875000
0$
0l"
0$#
#175000000
0!
1"
1#
1$
00
0E
1c
1x
19"
1N"
1l"
1$#
#178125000
0$
0l"
0$#
#181250000
0#
1$
09"
0N"
1l"
1$#
#184375000
0$
0l"
0$#
#187500000
0"
1#
1$
0c
0x
19"
1N"
1l"
1$#
#190625000
0$
0l"
0$#
#193750000
0#
1$
09"
0N"
1l"
1$#
#196875000
0$
0l"
0$#
#200000000
1!
1"
1#
1$
b0011 %
10
b0011 1
19
1E
b0011 F
1Q
1c
b0011 d
1l
1x
b0011 y
1'"
19"
b0011 :"
1B"
1N"
b0011 O"
1Z"
1l"
b0011 m"
1u"
1$#
b0011 %#
10#
#203125000
0$
0l"
0$#
#206250000
0#
1$
09"
0N"
1l"
1$#
#209375000
0$
0l"
0$#
#210000000
13
1;
1H
1S
1f
1n
1{
1)"
1<"
1D"
1Q"
1\"
1o"
1w"
1'#
12#
#212500000
0"
1#
1$
0c
0x
19"
1="
1H"
1K"
1N"
1R"
1`"
1c"
1f"
1l"
1p"
1{"
1!#
1$#
1(#
16#
19#
1<#
#215625000
0$
0l"
0$#
#218750000
0#
1$
09"
0N"
1l"
1$#
#221875000
0$
0l"
0$#
#222500000
1@"
1J"
1L"
0M"
1W"
1X"
0b"
1e"
1h"
1i"
1j"
1s"
1}"
1"#
0##
1-#
1.#
08#
1;#
1>#
1?#
1@#
#225000000
0!
1"
1#
1$
b10 *
b10 +
b10 .
b10 /
00
0E
1c
1g
1r
1u
1x
1|
1-"
10"
13"
19"
b10 ;"
1N"
b10 P"
1l"
b10 n"
1$#
b10 &#
#228125000
0$
0l"
0$#
#231250000
0#
1$
09"
0N"
1l"
1$#
#232500000
1A"
1M"
1V"
1k"
1t"
1##
1,#
1A#
#234375000
0$
0l"
0$#
#235000000
1j
1t
1v
0w
1$"
1%"
0/"
12"
15"
16"
17"
#237500000
0"
1#
1$
b11 *
b11 +
b11 .
b11 /
0c
0x
19"
b11 ;"
1N"
b11 P"
1l"
b11 n"
1$#
b11 &#
#240625000
0$
0l"
0$#
#243750000
0#
1$
09"
0N"
1l"
1$#
#245000000
1k
1w
1#"
18"
#246875000
0$
0l"
0$#
#250000000
1!
1"
1#
1$
b0100 %
b11 )
b11 -
10
b0100 1
14
09
0:
1<
1?
1B
1E
b0100 F
1I
0Q
0R
1T
1W
1Z
1]
1c
b0100 d
b11 e
0l
0m
1o
1x
b0100 y
b11 z
0'"
0("
1*"
19"
b0100 :"
0B"
0C"
1E"
1N"
b0100 O"
0Z"
0["
1]"
1l"
b0100 m"
0u"
0v"
1x"
1$#
b0100 %#
00#
01#
13#
#253125000
0$
0l"
0$#
#256250000
0#
1$
09"
0N"
1l"
1$#
#259375000
0$
0l"
0$#
#260000000
03
15
17
0;
1>
1A
1C
0D
0H
1J
1N
1O
0S
1V
0Y
1\
1_
1`
1a
0f
1h
0n
1q
0{
1}
0)"
1,"
0<"
1>"
0D"
1G"
0Q"
1S"
0\"
1_"
0o"
1q"
0w"
1z"
0'#
1)#
02#
15#
#262500000
0"
1#
1$
0c
0x
19"
0="
1?"
0H"
1I"
0K"
1N"
0R"
1T"
0`"
1a"
0c"
0f"
1g"
1l"
0p"
1r"
0{"
1|"
0!#
1$#
0(#
1*#
06#
17#
09#
0<#
1=#
#265625000
0$
0l"
0$#
#268750000
0#
1$
09"
0N"
1l"
1$#
#270000000
18
1D
1M
1b
#271875000
0$
0l"
0$#
#272500000
0A"
1J"
0M"
0X"
0b"
0e"
1h"
0i"
0t"
1}"
0##
0.#
08#
0;#
1>#
0?#
#275000000
0!
1"
1#
1$
b10 *
b10 +
00
0E
1c
0g
1i
0r
1s
0u
1x
0|
1!"
0-"
1."
00"
03"
14"
19"
b10 ;"
1N"
1l"
b10 n"
1$#
#278125000
0$
0l"
0$#
#281250000
0#
1$
09"
0N"
1l"
1$#
#282500000
0V"
0k"
0,#
0A#
#284375000
0$
0l"
0$#
#285000000
0k
1t
0w
0%"
0/"
02"
15"
06"
#287500000
0"
1#
1$
b10 .
b10 /
0c
0x
19"
1N"
b10 P"
1l"
1$#
b10 &#
#290625000
0$
0l"
0$#
#293750000
0#
1$
09"
0N"
1l"
1$#
#295000000
0#"
08"
#296875000
0$
0l"
0$#
#300000000
1!
1"
1#
1$
b0101 %
b11 (
b10 )
b11 ,
b10 -
10
b0101 1
b11 2
04
16
19
0?
1@
0B
1E
b0101 F
b11 G
0I
1K
1Q
0W
1X
0Z
0]
1^
1c
b0101 d
b10 e
1l
1x
b0101 y
b10 z
1'"
19"
b0101 :"
1B"
1N"
b0101 O"
1Z"
1l"
b0101 m"
1u"
1$#
b0101 %#
10#
#303125000
0$
0l"
0$#
#306250000
0#
1$
09"
0N"
1l"
1$#
#309375000
0$
0l"
0$#
#310000000
08
0;
1A
0D
0O
0S
0Y
0\
1_
0`
0n
0)"
0D"
0\"
0w"
02#
#312500000
0"
1#
1$
0c
0x
19"
1N"
1l"
1$#
#315625000
0$
0l"
0$#
#318750000
0#
1$
09"
0N"
1l"
1$#
#320000000
0M
0b
#321875000
0$
0l"
0$#
#325000000
0!
1"
1#
1$
00
0E
1c
1x
19"
1N"
1l"
1$#
#328125000
0$
0l"
0$#
#331250000
0#
1$
09"
0N"
1l"
1$#
#334375000
0$
0l"
0$#
#337500000
0"
1#
1$
0c
0x
19"
1N"
1l"
1$#
#340625000
0$
0l"
0$#
#343750000
0#
1$
09"
0N"
1l"
1$#
#346875000
0$
0l"
0$#
#350000000
1!
1"
1#
1$
b0110 %
b10 (
b10 ,
10
b0110 1
b10 2
09
1:
1E
b0110 F
b10 G
0Q
1R
1c
b0110 d
0l
1m
1x
b0110 y
0'"
1("
19"
b0110 :"
0B"
1C"
1N"
b0110 O"
0Z"
1["
1l"
b0110 m"
0u"
1v"
1$#
b0110 %#
00#
11#
#353125000
0$
0l"
0$#
#356250000
0#
1$
09"
0N"
1l"
1$#
#359375000
0$
0l"
0$#
#360000000
0;
0S
0n
0)"
0D"
0\"
0w"
02#
#362500000
0"
1#
1$
0c
0x
19"
1N"
1l"
1$#
#365625000
0$
0l"
0$#
#368750000
0#
1$
09"
0N"
1l"
1$#
#371875000
0$
0l"
0$#
#375000000
0!
1"
1#
1$
00
0E
1c
1x
19"
1N"
1l"
1$#
#378125000
0$
0l"
0$#
#381250000
0#
1$
09"
0N"
1l"
1$#
#384375000
0$
0l"
0$#
#387500000
0"
1#
1$
0c
0x
19"
1N"
1l"
1$#
#390625000
0$
0l"
0$#
#393750000
0#
1$
09"
0N"
1l"
1$#
#396875000
0$
0l"
0$#
#400000000
1!
1"
1#
1$
b0111 %
10
b0111 1
19
1E
b0111 F
1Q
1c
b0111 d
1l
1x
b0111 y
1'"
19"
b0111 :"
1B"
1N"
b0111 O"
1Z"
1l"
b0111 m"
1u"
1$#
b0111 %#
10#
#403125000
0$
0l"
0$#
#406250000
0#
1$
09"
0N"
1l"
1$#
#409375000
0$
0l"
0$#
#410000000
13
1;
1H
1S
1f
1n
1{
1)"
1<"
1D"
1Q"
1\"
1o"
1w"
1'#
12#
#412500000
0"
1#
1$
0c
0x
19"
1="
1H"
1K"
1N"
1R"
1`"
1c"
1f"
1l"
1p"
1{"
1!#
1$#
1(#
16#
19#
1<#
#415625000
0$
0l"
0$#
#418750000
0#
1$
09"
0N"
1l"
1$#
#421875000
0$
0l"
0$#
#422500000
0@"
1A"
0J"
0L"
1M"
0W"
1X"
1Y"
1b"
1d"
1e"
0h"
1i"
0j"
0s"
1t"
0}"
0"#
1##
0-#
1.#
1/#
18#
1:#
1;#
0>#
1?#
0@#
#425000000
0!
1"
1#
1$
b01 *
b01 +
b00 .
b00 /
00
0E
1c
1g
1r
1u
1x
1|
1-"
10"
13"
19"
b01 ;"
1N"
b00 P"
1l"
b01 n"
1$#
b00 &#
#428125000
0$
0l"
0$#
#431250000
0#
1$
09"
0N"
1l"
1$#
#432500000
0A"
0M"
0X"
0e"
0i"
0k"
0t"
0##
0.#
0;#
0?#
0A#
#434375000
0$
0l"
0$#
#435000000
0j
1k
0t
0v
1w
0$"
1%"
1&"
1/"
11"
12"
05"
16"
07"
#437500000
0"
1#
1$
b00 *
b00 +
0c
0x
19"
b00 ;"
1N"
1l"
b00 n"
1$#
#440625000
0$
0l"
0$#
#442500000
0k"
0A#
#443750000
0#
1$
09"
0N"
1l"
1$#
#445000000
0k
0w
0%"
02"
06"
08"
#446875000
0$
0l"
0$#
#450000000
1!
1"
1#
1$
b1000 %
b00 )
b00 -
10
b1000 1
14
09
0:
0<
1=
1?
1B
1E
b1000 F
1I
0Q
0R
0T
1U
1W
1Z
1]
1c
b1000 d
b00 e
0l
0m
0o
1p
1x
b1000 y
b00 z
0'"
0("
0*"
1+"
19"
b1000 :"
0B"
0C"
0E"
1F"
1N"
b1000 O"
0Z"
0["
0]"
1^"
1l"
b1000 m"
0u"
0v"
0x"
1y"
1$#
b1000 %#
00#
01#
03#
14#
#453125000
0$
0l"
0$#
#455000000
08"
#456250000
0#
1$
09"
0N"
1l"
1$#
#459375000
0$
0l"
0$#
