combin/delayed_ops/and2_d.vhd
library ieee;
use ieee.std_logic_1164.all;

entity and2_d is
    port (
        a : in std_logic;
        b : in std_logic;
        o : out std_logic
    );
end and2_d;

architecture rtl of and2_d is

begin

    o <= a and b after 10 ns;

end architecture;

combin/delayed_ops/xor2_d.vhd
library ieee;
use ieee.std_logic_1164.all;

entity xor2_d is
    port (
        a : in std_logic;
        b : in std_logic;
        o : out std_logic
    );
end xor2_d;

architecture rtl of xor2_d is

begin

    o <= a xor b after 10 ns;

end architecture;

combin/delayed_ops/or2_d.vhd
library ieee;
use ieee.std_logic_1164.all;

entity or2_d is
    port (
        a : in std_logic;
        b : in std_logic;
        o : out std_logic
    );
end or2_d;

architecture rtl of or2_d is

begin

    o <= a or b after 10 ns;

end architecture;

combin/mod_circ01.vhd
library ieee;
use ieee.std_logic_1164.all;
use ieee.numeric_std.all;
use work.delayed_operators.all;

entity mod_circ01 is
    port (
        i : in std_logic_vector(3 downto 0);
        o : out std_logic_vector(1 downto 0)
    );
end entity;

architecture rtl of mod_circ01 is

    signal s11,s12 : std_logic;

    -- Added signals 
    signal s21, s22, s23 : std_logic; -- could have been named sHT1 and sHT2

begin

    P11 : and2_d port map (i(0), i(1), s11);
    P12 : or2_d port map (i(2), i(3), s12);
    P21 : xor2_d port map (s11, s12, s21);
    o(1) <= s21;
    
    -- Added/modified relations 
    P22 : and2_d port map (s11, s12, s23);
    P23 : xor2_d port map (s11, s23, s22); 
    P24 : and2_d port map (s22,s21, o(0));

end architecture;

combin/circ01.vhd
library ieee;
use ieee.std_logic_1164.all;
use ieee.numeric_std.all;
use work.delayed_operators.all;

entity circ01 is
    port (
        i : in std_logic_vector(3 downto 0);
        o : out std_logic_vector(1 downto 0)
    );
end entity;

architecture rtl of circ01 is
    signal s11, s12, s21 : std_logic;
begin

    P11 : and2_d port map (i(0), i(1), s11);
    p12 : or2_d port map (i(2), i(3), s12);
    
    P21 : xor2_d port map (s11, s12, s21);
    P22 : and2_d port map (s11, s21, o(0));

    o(1) <= s21;

end architecture;

combin/tb_comp_combin.vhd
library ieee;
use ieee.std_logic_1164.all;
use ieee.numeric_std.all;
use work.delayed_operators.all;

entity tb_comp_combin is 
end entity;

architecture rtl of tb_comp_combin is

    constant T : time := 50 ns;

    procedure wait_cycles(n : natural) is
    begin
        for i in 0 to n-1 loop
            wait for T;
        end loop; 
    end procedure;

    procedure wait1 is
    begin
        wait for T;
    end procedure;


    signal clk_init : std_logic := '1';
    signal clk_2x : std_logic := '1';
    signal clk_4x : std_logic := '1';
    signal clk_8x : std_logic := '1';

    signal tb_input_vector : std_logic_vector(3 downto 0);
    signal tb_output_vector_auth : std_logic_vector(1 downto 0);
    signal tb_output_vector_inf : std_logic_vector(1 downto 0);

    signal tb_clk_init_output_auth : std_logic_vector(1 downto 0);
    signal tb_clk_2x_output_auth : std_logic_vector(1 downto 0);
    signal tb_clk_4x_output_auth : std_logic_vector(1 downto 0);
    signal tb_clk_8x_output_auth : std_logic_vector(1 downto 0);

    signal tb_clk_init_output_inf : std_logic_vector(1 downto 0);
    signal tb_clk_2x_output_inf : std_logic_vector(1 downto 0);
    signal tb_clk_4x_output_inf : std_logic_vector(1 downto 0);
    signal tb_clk_8x_output_inf : std_logic_vector(1 downto 0);

begin

    clk_init <= not(clk_init) after T/2;
    clk_2x <= not(clk_2x) after T/4;
    clk_4x <= not(clk_4x) after T/8;
    clk_8x <= not(clk_8x) after T/16;

    uut_auth : entity work.circ01 
    port map(
        i => tb_input_vector,
        o => tb_output_vector_auth
    );
    
    uut_inf : entity work.mod_circ01
    port map(
        i => tb_input_vector,
        o => tb_output_vector_inf
    );

    process 
    begin 
        for i in 0 to 15 loop
            wait1; 
            tb_input_vector <= std_logic_vector(to_unsigned(i, 4));
        end loop; 

        wait;
    end process;

    process(clk_init)
    begin
        if clk_init ='1' then
            tb_clk_init_output_auth <= tb_output_vector_auth;
            tb_clk_init_output_inf <= tb_output_vector_inf;
        end if;
    end process;

    process(clk_2x)
    begin
        if clk_2x = '1' then 
            tb_clk_2x_output_auth <= tb_output_vector_auth;
            tb_clk_2x_output_inf <= tb_output_vector_inf;
        end if;
    end process;

    process(clk_4x)
    begin
        if clk_4x = '1' then 
            tb_clk_4x_output_auth <= tb_output_vector_auth;
            tb_clk_4x_output_inf <= tb_output_vector_inf;
        end if;
    end process;

    process(clk_8x)
    begin
        if clk_8x = '1' then 
            tb_clk_8x_output_auth <= tb_output_vector_auth;
            tb_clk_8x_output_inf <= tb_output_vector_inf;
        end if;
    end process;

end architecture;

combin/test_comb.vcd
$date
  Mon Mar  6 11:10:36 2023
$end
$version
  GHDL v0
$end
$timescale
  1 fs
$end
$scope module standard $end
$upscope $end
$scope module std_logic_1164 $end
$upscope $end
$scope module numeric_std $end
$upscope $end
$scope module delayed_operators $end
$upscope $end
$scope module tb_comp_combin $end
$var reg 1 ! clk_init $end
$var reg 1 " clk_2x $end
$var reg 1 # clk_4x $end
$var reg 1 $ clk_8x $end
$var reg 4 % tb_input_vector[3:0] $end
$var reg 2 & tb_output_vector_auth[1:0] $end
$var reg 2 ' tb_output_vector_inf[1:0] $end
$var reg 2 ( tb_clk_init_output_auth[1:0] $end
$var reg 2 ) tb_clk_2x_output_auth[1:0] $end
$var reg 2 * tb_clk_4x_output_auth[1:0] $end
$var reg 2 + tb_clk_8x_output_auth[1:0] $end
$var reg 2 , tb_clk_init_output_inf[1:0] $end
$var reg 2 - tb_clk_2x_output_inf[1:0] $end
$var reg 2 . tb_clk_4x_output_inf[1:0] $end
$var reg 2 / tb_clk_8x_output_inf[1:0] $end
$scope module uut_auth $end
$var reg 4 0 i[3:0] $end
$var reg 2 1 o[1:0] $end
$var reg 1 2 s11 $end
$var reg 1 3 s12 $end
$var reg 1 4 s21 $end
$scope module p11 $end
$var reg 1 5 a $end
$var reg 1 6 b $end
$var reg 1 7 o $end
$upscope $end
$scope module p12 $end
$var reg 1 8 a $end
$var reg 1 9 b $end
$var reg 1 : o $end
$upscope $end
$scope module p21 $end
$var reg 1 ; a $end
$var reg 1 < b $end
$var reg 1 = o $end
$upscope $end
$scope module p22 $end
$var reg 1 > a $end
$var reg 1 ? b $end
$var reg 1 @ o $end
$upscope $end
$upscope $end
$scope module uut_inf $end
$var reg 4 A i[3:0] $end
$var reg 2 B o[1:0] $end
$var reg 1 C s11 $end
$var reg 1 D s12 $end
$var reg 1 E s21 $end
$var reg 1 F s22 $end
$var reg 1 G s23 $end
$scope module p11 $end
$var reg 1 H a $end
$var reg 1 I b $end
$var reg 1 J o $end
$upscope $end
$scope module p12 $end
$var reg 1 K a $end
$var reg 1 L b $end
$var reg 1 M o $end
$upscope $end
$scope module p21 $end
$var reg 1 N a $end
$var reg 1 O b $end
$var reg 1 P o $end
$upscope $end
$scope module p22 $end
$var reg 1 Q a $end
$var reg 1 R b $end
$var reg 1 S o $end
$upscope $end
$scope module p23 $end
$var reg 1 T a $end
$var reg 1 U b $end
$var reg 1 V o $end
$upscope $end
$scope module p24 $end
$var reg 1 W a $end
$var reg 1 X b $end
$var reg 1 Y o $end
$upscope $end
$upscope $end
$upscope $end
$enddefinitions $end
#0
1!
1"
1#
1$
bUUUU %
bUU &
bUU '
bUU (
bUU )
bUU *
bUU +
bUU ,
bUU -
bUU .
bUU /
bUUUU 0
bUU 1
U2
U3
U4
U5
U6
U7
U8
U9
U:
U;
U<
U=
U>
U?
U@
bUUUU A
bUU B
UC
UD
UE
UF
UG
UH
UI
UJ
UK
UL
UM
UN
UO
UP
UQ
UR
US
UT
UU
UV
UW
UX
UY
#3125000
0$
#6250000
0#
1$
#9375000
0$
#10000000
bUU 1
U7
U:
U=
U@
bUU B
UJ
UM
UP
US
UV
UY
#12500000
0"
1#
1$
#15625000
0$
#18750000
0#
1$
#21875000
0$
#25000000
0!
1"
1#
1$
#28125000
0$
#31250000
0#
1$
#34375000
0$
#37500000
0"
1#
1$
#40625000
0$
#43750000
0#
1$
#46875000
0$
#50000000
1!
1"
1#
1$
b0000 %
b0000 0
05
06
08
09
b0000 A
0H
0I
0K
0L
#53125000
0$
#56250000
0#
1$
#59375000
0$
#60000000
02
03
07
0:
0;
0<
0>
0C
0D
0J
0M
0N
0O
0Q
0R
0T
#62500000
0"
1#
1$
#65625000
0$
#68750000
0#
1$
#70000000
b00 &
b0U '
b00 1
04
0=
0?
0@
b0U B
0E
0G
0P
0S
0U
UV
0X
#71875000
0$
#75000000
0!
1"
1#
1$
b00 )
b00 *
b00 +
b0U -
b0U .
b0U /
#78125000
0$
#80000000
b00 '
b00 1
0@
b00 B
0F
0V
0W
0Y
#81250000
0#
1$
b00 /
#84375000
0$
#87500000
0"
1#
1$
b00 .
#90000000
b00 B
0Y
#90625000
0$
#93750000
0#
1$
#96875000
0$
#100000000
1!
1"
1#
1$
b0001 %
b00 (
b00 ,
b00 -
b0001 0
15
b0001 A
1H
#103125000
0$
#106250000
0#
1$
#109375000
0$
#110000000
07
0J
#112500000
0"
1#
1$
#115625000
0$
#118750000
0#
1$
#121875000
0$
#125000000
0!
1"
1#
1$
#128125000
0$
#131250000
0#
1$
#134375000
0$
#137500000
0"
1#
1$
#140625000
0$
#143750000
0#
1$
#146875000
0$
#150000000
1!
1"
1#
1$
b0010 %
b0010 0
05
16
b0010 A
0H
1I
#153125000
0$
#156250000
0#
1$
#159375000
0$
#160000000
07
0J
#162500000
0"
1#
1$
#165625000
0$
#168750000
0#
1$
#171875000
0$
#175000000
0!
1"
1#
1$
#178125000
0$
#181250000
0#
1$
#184375000
0$
#187500000
0"
1#
1$
#190625000
0$
#193750000
0#
1$
#196875000
0$
#200000000
1!
1"
1#
1$
b0011 %
b0011 0
15
b0011 A
1H
#203125000
0$
#206250000
0#
1$
#209375000
0$
#210000000
12
17
1;
1>
1C
1J
1N
1Q
1T
#212500000
0"
1#
1$
#215625000
0$
#218750000
0#
1$
#220000000
b10 &
b10 '
b10 1
14
1=
1?
0@
b10 B
1E
1F
1P
0S
1V
1W
1X
#221875000
0$
#225000000
0!
1"
1#
1$
b10 )
b10 *
b10 +
b10 -
b10 .
b10 /
#228125000
0$
#230000000
b11 &
b11 '
b11 1
1@
b11 B
1Y
#231250000
0#
1$
b11 +
b11 /
#234375000
0$
#237500000
0"
1#
1$
b11 *
b11 .
#240625000
0$
#243750000
0#
1$
#246875000
0$
#250000000
1!
1"
1#
1$
b0100 %
b11 (
b11 )
b11 ,
b11 -
b0100 0
05
06
18
b0100 A
0H
0I
1K
#253125000
0$
#256250000
0#
1$
#259375000
0$
#260000000
02
13
07
1:
0;
1<
0>
0C
1D
0J
1M
0N
1O
0Q
1R
0T
#262500000
0"
1#
1$
#265625000
0$
#268750000
0#
1$
#270000000
b10 &
b10 1
1=
0@
0F
1P
0S
0V
0W
#271875000
0$
#275000000
0!
1"
1#
1$
b10 )
b10 *
b10 +
#278125000
0$
#280000000
b10 '
b10 B
0Y
#281250000
0#
1$
b10 /
#284375000
0$
#287500000
0"
1#
1$
b10 .
#290625000
0$
#293750000
0#
1$
#296875000
0$
#300000000
1!
1"
1#
1$
b0101 %
b10 (
b10 ,
b10 -
b0101 0
15
b0101 A
1H
#303125000
0$
#306250000
0#
1$
#309375000
0$
#310000000
07
0J
#312500000
0"
1#
1$
#315625000
0$
#318750000
0#
1$
#321875000
0$
#325000000
0!
1"
1#
1$
#328125000
0$
#331250000
0#
1$
#334375000
0$
#337500000
0"
1#
1$
#340625000
0$
#343750000
0#
1$
#346875000
0$
#350000000
1!
1"
1#
1$
b0110 %
b0110 0
05
16
b0110 A
0H
1I
#353125000
0$
#356250000
0#
1$
#359375000
0$
#360000000
07
0J
#362500000
0"
1#
1$
#365625000
0$
#368750000
0#
1$
#371875000
0$
#375000000
0!
1"
1#
1$
#378125000
0$
#381250000
0#
1$
#384375000
0$
#387500000
0"
1#
1$
#390625000
0$
#393750000
0#
1$
#396875000
0$
#400000000
1!
1"
1#
1$
b0111 %
b0111 0
15
b0111 A
1H
#403125000
0$
#406250000
0#
1$
#409375000
0$
#410000000
12
17
1;
1>
1C
1J
1N
1Q
1T
#412500000
0"
1#
1$
#415625000
0$
#418750000
0#
1$
#420000000
b01 &
b00 '
b01 1
04
0=
0?
1@
b00 B
0E
1F
1G
0P
1S
1U
1V
1W
0X
#421875000
0$
#425000000
0!
1"
1#
1$
b01 )
b01 *
b01 +
b00 -
b00 .
b00 /
#428125000
0$
#430000000
b00 &
b00 1
0@
b00 B
0F
0V
0W
0Y
#431250000
0#
1$
b00 +
#434375000
0$
#437500000
0"
1#
1$
b00 *
#440000000
b00 B
0Y
#440625000
0$
#443750000
0#
1$
#446875000
0$
#450000000
1!
1"
1#
1$
b1000 %
b00 (
b00 )
b00 ,
b1000 0
05
06
08
19
b1000 A
0H
0I
0K
1L
#453125000
0$
#456250000
0#
1$
#459375000
0$
#460000000
02
07
1:
0;
0>
0C
0J
1M
0N
0Q
0T
#462500000
0"
1#
1$
#465625000
0$
#468750000
0#
1$
#470000000
b10 &
b10 '
b10 1
14
1=
1?
0@
b10 B
1E
1F
0G
1P
0S
0U
1V
1W
1X
#471875000
0$
#475000000
0!
1"
1#
1$
b10 )
b10 *
b10 +
b10 -
b10 .
b10 /
#478125000
0$
#480000000
b11 '
b10 1
0@
b11 B
0F
0V
0W
1Y
#481250000
0#
1$
b11 /
#484375000
0$
#487500000
0"
1#
1$
b11 .
#490000000
b10 '
b10 B
0Y
#490625000
0$
#493750000
0#
1$
b10 /
#496875000
0$
#500000000
1!
1"
1#
1$
b1001 %
b10 (
b10 ,
b10 .
b1001 0
15
b1001 A
1H
#503125000
0$
#506250000
0#
1$
#509375000
0$
#510000000
07
0J
#512500000
0"
1#
1$
#515625000
0$
#518750000
0#
1$
#521875000
0$
#525000000
0!
1"
1#
1$
#528125000
0$
#531250000
0#
1$
#534375000
0$
#537500000
0"
1#
1$
#540625000
0$
#543750000
0#
1$
#546875000
0$
#550000000
1!
1"
1#
1$
b1010 %
b1010 0
05
16
b1010 A
0H
1I
#553125000
0$
#556250000
0#
1$
#559375000
0$
#560000000
07
0J
#562500000
0"
1#
1$
#565625000
0$
#568750000
0#
1$
#571875000
0$
#575000000
0!
1"
1#
1$
#578125000
0$
#581250000
0#
1$
#584375000
0$
#587500000
0"
1#
1$
#590625000
0$
#593750000
0#
1$
#596875000
0$
#600000000
1!
1"
1#
1$
b1011 %
b1011 0
15
b1011 A
1H
#603125000
0$
#606250000
0#
1$
#609375000
0$
#610000000
12
17
1;
1>
1C
1J
1N
1Q
1T
#612500000
0"
1#
1$
#615625000
0$
#618750000
0#
1$
#620000000
b01 &
b00 '
b01 1
04
0=
0?
1@
b00 B
0E
1F
1G
0P
1S
1U
1V
1W
0X
#621875000
0$
#625000000
0!
1"
1#
1$
b01 )
b01 *
b01 +
b00 -
b00 .
b00 /
#628125000
0$
#630000000
b00 &
b00 1
0@
b00 B
0F
0V
0W
0Y
#631250000
0#
1$
b00 +
#634375000
0$
#637500000
0"
1#
1$
b00 *
#640000000
b00 B
0Y
#640625000
0$
#643750000
0#
1$
#646875000
0$
#650000000
1!
1"
1#
1$
b1100 %
b00 (
b00 )
b00 ,
b1100 0
05
06
18
b1100 A
0H
0I
1K
#653125000
0$
#656250000
0#
1$
#659375000
0$
#660000000
02
07
1:
0;
0>
0C
0J
1M
0N
0Q
0T
#662500000
0"
1#
1$
#665625000
0$
#668750000
0#
1$
#670000000
b10 &
b10 '
b10 1
14
1=
1?
0@
b10 B
1E
1F
0G
1P
0S
0U
1V
1W
1X
#671875000
0$
#675000000
0!
1"
1#
1$
b10 )
b10 *
b10 +
b10 -
b10 .
b10 /
#678125000
0$
#680000000
b11 '
b10 1
0@
b11 B
0F
0V
0W
1Y
#681250000
0#
1$
b11 /
#684375000
0$
#687500000
0"
1#
1$
b11 .
#690000000
b10 '
b10 B
0Y
#690625000
0$
#693750000
0#
1$
b10 /
#696875000
0$
#700000000
1!
1"
1#
1$
b1101 %
b10 (
b10 ,
b10 .
b1101 0
15
b1101 A
1H
#703125000
0$
#706250000
0#
1$
#709375000
0$
#710000000
07
0J
#712500000
0"
1#
1$
#715625000
0$
#718750000
0#
1$
#721875000
0$
#725000000
0!
1"
1#
1$
#728125000
0$
#731250000
0#
1$
#734375000
0$
#737500000
0"
1#
1$
#740625000
0$
#743750000
0#
1$
#746875000
0$
#750000000
1!
1"
1#
1$
b1110 %
b1110 0
05
16
b1110 A
0H
1I
#753125000
0$
#756250000
0#
1$
#759375000
0$
#760000000
07
0J
#762500000
0"
1#
1$
#765625000
0$
#768750000
0#
1$
#771875000
0$
#775000000
0!
1"
1#
1$
#778125000
0$
#781250000
0#
1$
#784375000
0$
#787500000
0"
1#
1$
#790625000
0$
#793750000
0#
1$
#796875000
0$
#800000000
1!
1"
1#
1$
b1111 %
b1111 0
15
b1111 A
1H
#803125000
0$
#806250000
0#
1$
#809375000
0$
#810000000
12
17
1;
1>
1C
1J
1N
1Q
1T
#812500000
0"
1#
1$
#815625000
0$
#818750000
0#
1$
#820000000
b01 &
b00 '
b01 1
04
0=
0?
1@
b00 B
0E
1F
1G
0P
1S
1U
1V
1W
0X
#821875000
0$
#825000000
0!
1"
1#
1$
b01 )
b01 *
b01 +
b00 -
b00 .
b00 /
#828125000
0$
#830000000
b00 &
b00 1
0@
b00 B
0F
0V
0W
0Y
#831250000
0#
1$
b00 +
#834375000
0$
#837500000
0"
1#
1$
b00 *
#840000000
b00 B
0Y
#840625000
0$
#843750000
0#
1$
#846875000
0$
#850000000
1!
1"
1#
1$
b00 (
b00 )
b00 ,
