combin/delayed_ops/and2_d.vhd
library ieee;
use ieee.std_logic_1164.all;

entity and2_d is
    port (
        a : in std_logic;
        b : in std_logic;
        o : out std_logic
    );
end and2_d;

architecture rtl of and2_d is

begin

    o <= a and b after 10 ns;

end architecture;

combin/delayed_ops/xor2_d.vhd
library ieee;
use ieee.std_logic_1164.all;

entity xor2_d is
    port (
        a : in std_logic;
        b : in std_logic;
        o : out std_logic
    );
end xor2_d;

architecture rtl of xor2_d is

begin

    o <= a xor b after 10 ns;

end architecture;

combin/delayed_ops/or2_d.vhd
library ieee;
use ieee.std_logic_1164.all;

entity or2_d is
    port (
        a : in std_logic;
        b : in std_logic;
        o : out std_logic
    );
end or2_d;

architecture rtl of or2_d is

begin

    o <= a or b after 10 ns;

end architecture;

combin/mod_circ01.vhd
library ieee;
use ieee.std_logic_1164.all;
use ieee.numeric_std.all;
use work.delayed_operators.all;

entity mod_circ01 is
    port (
        i : in std_logic_vector(3 downto 0);
        o : out std_logic_vector(1 downto 0)
    );
end entity;

architecture rtl of mod_circ01 is

    signal s11,s12 : std_logic;

    -- Added signals 
    signal s21, s22, s23 : std_logic; -- could have been named sHT1 and sHT2

begin

    P11 : and2_d port map (i(0), i(1), s11);
    P12 : or2_d port map (i(2), i(3), s12);
    P21 : xor2_d port map (s11, s12, s21);
    o(1) <= s21;
    
    -- Added/modified relations 
    P22 : and2_d port map (s11, s12, s23);
    P23 : xor2_d port map (s11, s23, s22); 
    P24 : and2_d port map (s22,s21, o(0));

end architecture;

combin/circ01.vhd
library ieee;
use ieee.std_logic_1164.all;
use ieee.numeric_std.all;
use work.delayed_operators.all;

entity circ01 is
    port (
        i : in std_logic_vector(3 downto 0);
        o : out std_logic_vector(1 downto 0)
    );
end entity;

architecture rtl of circ01 is
    signal s11, s12, s21 : std_logic;
begin

    P11 : and2_d port map (i(0), i(1), s11);
    p12 : or2_d port map (i(2), i(3), s12);
    
    P21 : xor2_d port map (s11, s12, s21);
    P22 : and2_d port map (s11, s21, o(0));

    o(1) <= s21;

end architecture;

combin/tb_comp_combin.vhd
library ieee;
use ieee.std_logic_1164.all;
use ieee.numeric_std.all;
use work.delayed_operators.all;

entity tb_comp_combin is 
end entity;

architecture rtl of tb_comp_combin is

    constant T : time := 50 ns;

    procedure wait_cycles(n : natural) is
    begin
        for i in 0 to n-1 loop
            wait for T;
        end loop; 
    end procedure;

    procedure wait1 is
    begin
        wait for T;
    end procedure;


    signal clk_init : std_logic := '1';
    signal clk_2x : std_logic := '1';
    signal clk_4x : std_logic := '1';
    signal clk_8x : std_logic := '1';

    signal tb_input_vector : std_logic_vector(3 downto 0);
    signal tb_output_vector_auth : std_logic_vector(1 downto 0);
    signal tb_output_vector_inf : std_logic_vector(1 downto 0);

    signal tb_clk_init_output_auth : std_logic_vector(1 downto 0);
    signal tb_clk_2x_output_auth : std_logic_vector(1 downto 0);
    signal tb_clk_4x_output_auth : std_logic_vector(1 downto 0);
    signal tb_clk_8x_output_auth : std_logic_vector(1 downto 0);

    signal tb_clk_init_output_inf : std_logic_vector(1 downto 0);
    signal tb_clk_2x_output_inf : std_logic_vector(1 downto 0);
    signal tb_clk_4x_output_inf : std_logic_vector(1 downto 0);
    signal tb_clk_8x_output_inf : std_logic_vector(1 downto 0);

begin

    clk_init <= not(clk_init) after T/2;
    clk_2x <= not(clk_2x) after T/4;
    clk_4x <= not(clk_4x) after T/8;
    clk_8x <= not(clk_8x) after T/16;

    uut_auth : entity work.circ01 
    port map(
        i => tb_input_vector,
        o => tb_output_vector_auth
    );
    
    uut_inf : entity work.mod_circ01
    port map(
        i => tb_input_vector,
        o => tb_output_vector_inf
    );

    process 
    begin 
        for i in 0 to 15 loop
            wait1; 
            tb_input_vector <= std_logic_vector(to_unsigned(i, 4));
        end loop; 

        wait;
    end process;

    process(clk_init)
    begin
        if clk_init ='1' then
            tb_clk_init_output_auth <= tb_output_vector_auth;
            tb_clk_init_output_inf <= tb_output_vector_inf;
        end if;
    end process;

    process(clk_2x)
    begin
        if clk_2x = '1' then 
            tb_clk_2x_output_auth <= tb_output_vector_auth;
            tb_clk_2x_output_inf <= tb_output_vector_inf;
        end if;
    end process;

    process(clk_4x)
    begin
        if clk_4x = '1' then 
            tb_clk_4x_output_auth <= tb_output_vector_auth;
            tb_clk_4x_output_inf <= tb_output_vector_inf;
        end if;
    end process;

    process(clk_8x)
    begin
        if clk_8x = '1' then 
            tb_clk_8x_output_auth <= tb_output_vector_auth;
            tb_clk_8x_output_inf <= tb_output_vector_inf;
        end if;
    end process;

end architecture;

combin/test_seq.vcd
$date
  Fri Mar  3 17:16:23 2023
$end
$version
  GHDL v0
$end
$timescale
  1 fs
$end
$scope module standard $end
$upscope $end
$scope module std_logic_1164 $end
$upscope $end
$scope module numeric_std $end
$upscope $end
$scope module delayed_operators $end
$upscope $end
$scope module tb_comp_combin $end
$var reg 1 ! clk_init $end
$var reg 1 " clk_2x $end
$var reg 1 # clk_4x $end
$var reg 1 $ clk_8x $end
$var reg 4 % tb_input_vector[3:0] $end
$var reg 2 & tb_output_vector_auth[1:0] $end
$var reg 2 ' tb_output_vector_inf[1:0] $end
$var reg 2 ( tb_clk_init_output_auth[1:0] $end
$var reg 2 ) tb_clk_2x_output_auth[1:0] $end
$var reg 2 * tb_clk_4x_output_auth[1:0] $end
$var reg 2 + tb_clk_8x_output_auth[1:0] $end
$var reg 2 , tb_clk_init_output_inf[1:0] $end
$var reg 2 - tb_clk_2x_output_inf[1:0] $end
$var reg 2 . tb_clk_4x_output_inf[1:0] $end
$var reg 2 / tb_clk_8x_output_inf[1:0] $end
$scope module uut_auth $end
$var reg 4 0 i[3:0] $end
$var reg 2 1 o[1:0] $end
$var reg 1 2 s11 $end
$var reg 1 3 s12 $end
$var reg 1 4 s21 $end
$upscope $end
$scope module uut_inf $end
$var reg 4 5 i[3:0] $end
$var reg 2 6 o[1:0] $end
$var reg 1 7 s11 $end
$var reg 1 8 s12 $end
$var reg 1 9 s21 $end
$var reg 1 : s22 $end
$var reg 1 ; s23 $end
$upscope $end
$upscope $end
$enddefinitions $end
#0
1!
1"
1#
1$
bUUUU %
bUU &
bUU '
bUU (
bUU )
bUU *
bUU +
bUU ,
bUU -
bUU .
bUU /
bUUUU 0
bUU 1
U2
U3
U4
bUUUU 5
bUU 6
U7
U8
U9
U:
U;
#6250000
0$
#10000000
bUU 1
bUU 6
#12500000
0#
1$
#18750000
0$
#25000000
0"
1#
1$
#31250000
0$
#37500000
0#
1$
#43750000
0$
#50000000
0!
1"
1#
1$
#56250000
0$
#62500000
0#
1$
#68750000
0$
#75000000
0"
1#
1$
#81250000
0$
#87500000
0#
1$
#93750000
0$
#100000000
1!
1"
1#
1$
b0000 %
b0000 0
b0000 5
#106250000
0$
#110000000
02
03
07
08
#112500000
0#
1$
#118750000
0$
#120000000
b00 &
b0U '
b00 1
04
b0U 6
09
0;
#125000000
0"
1#
1$
b00 *
b00 +
b0U .
b0U /
#130000000
b00 '
b00 1
b00 6
0:
#131250000
0$
#137500000
0#
1$
b00 /
#140000000
b00 6
#143750000
0$
#150000000
0!
1"
1#
1$
b00 )
b00 -
b00 .
#156250000
0$
#162500000
0#
1$
#168750000
0$
#175000000
0"
1#
1$
#181250000
0$
#187500000
0#
1$
#193750000
0$
#200000000
1!
1"
1#
1$
b0001 %
b00 (
b00 ,
b0001 0
b0001 5
#206250000
0$
#210000000
#212500000
0#
1$
#218750000
0$
#225000000
0"
1#
1$
#231250000
0$
#237500000
0#
1$
#243750000
0$
#250000000
0!
1"
1#
1$
#256250000
0$
#262500000
0#
1$
#268750000
0$
#275000000
0"
1#
1$
#281250000
0$
#287500000
0#
1$
#293750000
0$
#300000000
1!
1"
1#
1$
b0010 %
b0010 0
b0010 5
#306250000
0$
#310000000
#312500000
0#
1$
#318750000
0$
#325000000
0"
1#
1$
#331250000
0$
#337500000
0#
1$
#343750000
0$
#350000000
0!
1"
1#
1$
#356250000
0$
#362500000
0#
1$
#368750000
0$
#375000000
0"
1#
1$
#381250000
0$
#387500000
0#
1$
#393750000
0$
#400000000
1!
1"
1#
1$
b0011 %
b0011 0
b0011 5
#406250000
0$
#410000000
12
17
#412500000
0#
1$
#418750000
0$
#420000000
b10 &
b10 '
b10 1
14
b10 6
19
1:
#425000000
0"
1#
1$
b10 *
b10 +
b10 .
b10 /
#430000000
b11 &
b11 '
b11 1
b11 6
#431250000
0$
#437500000
0#
1$
b11 +
b11 /
#443750000
0$
#450000000
0!
1"
1#
1$
b11 )
b11 *
b11 -
b11 .
#456250000
0$
#462500000
0#
1$
#468750000
0$
#475000000
0"
1#
1$
#481250000
0$
#487500000
0#
1$
#493750000
0$
#500000000
1!
1"
1#
1$
b0100 %
b11 (
b11 ,
b0100 0
b0100 5
#506250000
0$
#510000000
02
13
07
18
#512500000
0#
1$
#518750000
0$
#520000000
b10 &
b10 1
0:
#525000000
0"
1#
1$
b10 *
b10 +
#530000000
b10 '
b10 6
#531250000
0$
#537500000
0#
1$
b10 /
#543750000
0$
#550000000
0!
1"
1#
1$
b10 )
b10 -
b10 .
#556250000
0$
#562500000
0#
1$
#568750000
0$
#575000000
0"
1#
1$
#581250000
0$
#587500000
0#
1$
#593750000
0$
#600000000
1!
1"
1#
1$
b0101 %
b10 (
b10 ,
b0101 0
b0101 5
#606250000
0$
#610000000
#612500000
0#
1$
#618750000
0$
#625000000
0"
1#
1$
#631250000
0$
#637500000
0#
1$
#643750000
0$
#650000000
0!
1"
1#
1$
#656250000
0$
#662500000
0#
1$
#668750000
0$
#675000000
0"
1#
1$
#681250000
0$
#687500000
0#
1$
#693750000
0$
#700000000
1!
1"
1#
1$
b0110 %
b0110 0
b0110 5
#706250000
0$
#710000000
#712500000
0#
1$
#718750000
0$
#725000000
0"
1#
1$
#731250000
0$
#737500000
0#
1$
#743750000
0$
#750000000
0!
1"
1#
1$
#756250000
0$
#762500000
0#
1$
#768750000
0$
#775000000
0"
1#
1$
#781250000
0$
#787500000
0#
1$
#793750000
0$
#800000000
1!
1"
1#
1$
b0111 %
b0111 0
b0111 5
#806250000
0$
#810000000
12
17
#812500000
0#
1$
#818750000
0$
#820000000
b01 &
b00 '
b01 1
04
b00 6
09
1:
1;
#825000000
0"
1#
1$
b01 *
b01 +
b00 .
b00 /
#830000000
b00 &
b00 1
b00 6
0:
#831250000
0$
#837500000
0#
1$
b00 +
#840000000
b00 6
#843750000
0$
#850000000
0!
1"
1#
1$
b00 )
b00 *
b00 -
#856250000
0$
#862500000
0#
1$
#868750000
0$
#875000000
0"
1#
1$
#881250000
0$
#887500000
0#
1$
#893750000
0$
#900000000
1!
1"
1#
1$
b1000 %
b00 (
b00 ,
b1000 0
b1000 5
#906250000
0$
#910000000
02
07
#912500000
0#
1$
#918750000
0$
#920000000
b10 &
b10 '
b10 1
14
b10 6
19
1:
0;
#925000000
0"
1#
1$
b10 *
b10 +
b10 .
b10 /
#930000000
b11 '
b10 1
b11 6
0:
#931250000
0$
#937500000
0#
1$
b11 /
#940000000
b10 '
b10 6
#943750000
0$
#950000000
0!
1"
1#
1$
b10 )
b10 -
b10 /
#956250000
0$
#962500000
0#
1$
#968750000
0$
#975000000
0"
1#
1$
#981250000
0$
#987500000
0#
1$
#993750000
0$
#1000000000
1!
1"
1#
1$
b1001 %
b10 (
b10 ,
b1001 0
b1001 5
#1006250000
0$
#1010000000
#1012500000
0#
1$
#1018750000
0$
#1025000000
0"
1#
1$
#1031250000
0$
#1037500000
0#
1$
#1043750000
0$
#1050000000
0!
1"
1#
1$
#1056250000
0$
#1062500000
0#
1$
#1068750000
0$
#1075000000
0"
1#
1$
#1081250000
0$
#1087500000
0#
1$
#1093750000
0$
#1100000000
1!
1"
1#
1$
b1010 %
b1010 0
b1010 5
#1106250000
0$
#1110000000
#1112500000
0#
1$
#1118750000
0$
#1125000000
0"
1#
1$
#1131250000
0$
#1137500000
0#
1$
#1143750000
0$
#1150000000
0!
1"
1#
1$
#1156250000
0$
#1162500000
0#
1$
#1168750000
0$
#1175000000
0"
1#
1$
#1181250000
0$
#1187500000
0#
1$
#1193750000
0$
#1200000000
1!
1"
1#
1$
b1011 %
b1011 0
b1011 5
#1206250000
0$
#1210000000
12
17
#1212500000
0#
1$
#1218750000
0$
#1220000000
b01 &
b00 '
b01 1
04
b00 6
09
1:
1;
#1225000000
0"
1#
1$
b01 *
b01 +
b00 .
b00 /
#1230000000
b00 &
b00 1
b00 6
0:
#1231250000
0$
#1237500000
0#
1$
b00 +
#1240000000
b00 6
#1243750000
0$
#1250000000
0!
1"
1#
1$
b00 )
b00 *
b00 -
#1256250000
0$
#1262500000
0#
1$
#1268750000
0$
#1275000000
0"
1#
1$
#1281250000
0$
#1287500000
0#
1$
#1293750000
0$
#1300000000
1!
1"
1#
1$
b1100 %
b00 (
b00 ,
b1100 0
b1100 5
#1306250000
0$
#1310000000
02
07
#1312500000
0#
1$
#1318750000
0$
#1320000000
b10 &
b10 '
b10 1
14
b10 6
19
1:
0;
#1325000000
0"
1#
1$
b10 *
b10 +
b10 .
b10 /
#1330000000
b11 '
b10 1
b11 6
0:
#1331250000
0$
#1337500000
0#
1$
b11 /
#1340000000
b10 '
b10 6
#1343750000
0$
#1350000000
0!
1"
1#
1$
b10 )
b10 -
b10 /
#1356250000
0$
#1362500000
0#
1$
#1368750000
0$
#1375000000
0"
1#
1$
#1381250000
0$
#1387500000
0#
1$
#1393750000
0$
#1400000000
1!
1"
1#
1$
b1101 %
b10 (
b10 ,
b1101 0
b1101 5
#1406250000
0$
#1410000000
#1412500000
0#
1$
#1418750000
0$
#1425000000
0"
1#
1$
#1431250000
0$
#1437500000
0#
1$
#1443750000
0$
#1450000000
0!
1"
1#
1$
#1456250000
0$
#1462500000
0#
1$
#1468750000
0$
#1475000000
0"
1#
1$
#1481250000
0$
#1487500000
0#
1$
#1493750000
0$
#1500000000
1!
1"
1#
1$
b1110 %
b1110 0
b1110 5
#1506250000
0$
#1510000000
#1512500000
0#
1$
#1518750000
0$
#1525000000
0"
1#
1$
#1531250000
0$
#1537500000
0#
1$
#1543750000
0$
#1550000000
0!
1"
1#
1$
#1556250000
0$
#1562500000
0#
1$
#1568750000
0$
#1575000000
0"
1#
1$
#1581250000
0$
#1587500000
0#
1$
#1593750000
0$
#1600000000
1!
1"
1#
1$
b1111 %
b1111 0
b1111 5
#1606250000
0$
#1610000000
12
17
#1612500000
0#
1$
#1618750000
0$
#1620000000
b01 &
b00 '
b01 1
04
b00 6
09
1:
1;
#1625000000
0"
1#
1$
b01 *
b01 +
b00 .
b00 /
#1630000000
b00 &
b00 1
b00 6
0:
#1631250000
0$
#1637500000
0#
1$
b00 +
#1640000000
b00 6
#1643750000
0$
#1650000000
0!
1"
1#
1$
b00 )
b00 *
b00 -
#1656250000
0$
#1662500000
0#
1$
#1668750000
0$
#1675000000
0"
1#
1$
#1681250000
0$
#1687500000
0#
1$
#1693750000
0$
#1700000000
1!
1"
1#
1$
b00 (
b00 ,
